CODE_OF_CONDUCT.md
CONTRIBUTING.md
LICENSE
NOTICE
README.md
THIRD-PARTY
cloudsaga/__init__.py
cloudsaga/cloudsaga.py
cloudsaga/scenarios/__init__.py
cloudsaga/scenarios/iam_credentials.py
cloudsaga/scenarios/imds_reveal.py
cloudsaga/scenarios/mining_bitcoin.py
cloudsaga/scenarios/network_changes.py
cloudsaga/scenarios/public_resources.py
cloudsaga-1.0.1.dist-info/entry_points.txt
cloudsaga-1.0.1.dist-info/LICENSE
cloudsaga-1.0.1.dist-info/WHEEL
cloudsaga-1.0.1.dist-info/METADATA
cloudsaga-1.0.1.dist-info/RECORD
