Metadata-Version: 2.1
Name: cloudsaga
Version: 1.0.1
Summary: AWS CloudSaga is a tool to test security controls and alerts within their Amazon Web Services (AWS) environment
Home-page: https://github.com/awslabs/aws-cloudsaga
Author: Joshua McKiddy
Requires-Python: >=3.7,<4.0
Classifier: Programming Language :: Python :: 3
Classifier: Programming Language :: Python :: 3.10
Classifier: Programming Language :: Python :: 3.7
Classifier: Programming Language :: Python :: 3.8
Classifier: Programming Language :: Python :: 3.9
Requires-Dist: boto3 (>=1.21.7,<2.0.0)
Project-URL: Repository, https://github.com/awslabs/aws-cloudsaga
